ng_data_pipelines_sdk/__init__.py
ng_data_pipelines_sdk/aws_interface.py
ng_data_pipelines_sdk/custom_logger.py
ng_data_pipelines_sdk/dataframe_manager.py
ng_data_pipelines_sdk/interfaces.py
ng_data_pipelines_sdk/spark_manager.py
ng_data_pipelines_sdk/utils.py
ng_data_pipelines_sdk-1.21.3.dist-info/METADATA
ng_data_pipelines_sdk-1.21.3.dist-info/WHEEL
ng_data_pipelines_sdk-1.21.3.dist-info/RECORD
